Metadata-Version: 2.1
Name: image-processing-oliveira
Version: 0.0.1
Summary: NTT DATA bootcamp
Home-page: https://github.com/daniel-neves-dev/image_processing_dio.git
Author: DanielOliveira
Author-email: danielnevesoliveira052@gmail.com
License: UNKNOWN
Platform: UNKNOWN
Requires-Python: >=3.8
